oxyde/__init__.py
oxyde/exceptions.py
oxyde/py.typed
oxyde/cli/__init__.py
oxyde/cli/app.py
oxyde/cli/codegen.py
oxyde/cli/config.py
oxyde/cli/migrations.py
oxyde/codegen/__init__.py
oxyde/codegen/stub_generator.py
oxyde/core/__init__.py
oxyde/core/ir.py
oxyde/core/ir_types.py
oxyde/core/wrapper.py
oxyde/db/__init__.py
oxyde/db/pool.py
oxyde/db/registry.py
oxyde/db/transaction.py
oxyde/migrations/__init__.py
oxyde/migrations/config.py
oxyde/migrations/context.py
oxyde/migrations/executor.py
oxyde/migrations/extract.py
oxyde/migrations/generator.py
oxyde/migrations/replay.py
oxyde/migrations/tracker.py
oxyde/migrations/types.py
oxyde/models/__init__.py
oxyde/models/base.py
oxyde/models/decorators.py
oxyde/models/field.py
oxyde/models/lookups.py
oxyde/models/metadata.py
oxyde/models/registry.py
oxyde/models/serializers.py
oxyde/models/utils.py
oxyde/queries/__init__.py
oxyde/queries/aggregates.py
oxyde/queries/base.py
oxyde/queries/conditions.py
oxyde/queries/expressions.py
oxyde/queries/insert.py
oxyde/queries/joins.py
oxyde/queries/manager.py
oxyde/queries/q.py
oxyde/queries/raw.py
oxyde/queries/select.py
oxyde/queries/mixins/__init__.py
oxyde/queries/mixins/aggregation.py
oxyde/queries/mixins/debug.py
oxyde/queries/mixins/execution.py
oxyde/queries/mixins/filtering.py
oxyde/queries/mixins/joining.py
oxyde/queries/mixins/mutation.py
oxyde/queries/mixins/pagination.py
oxyde-0.3.1.dist-info/METADATA
oxyde-0.3.1.dist-info/WHEEL
oxyde-0.3.1.dist-info/entry_points.txt
oxyde-0.3.1.dist-info/top_level.txt
oxyde-0.3.1.dist-info/RECORD
