Metadata-Version: 2.4
Name: oxyde
Version: 0.3.1
Summary: High-performance async Python ORM with Rust core
Author-email: Nikita Ryzhenkov <nikita.ryzhenkoff@gmail.com>
License: MIT
Project-URL: Homepage, https://github.com/mr-fatalyst/oxyde
Project-URL: Documentation, https://github.com/mr-fatalyst/oxyde#readme
Project-URL: Repository, https://github.com/mr-fatalyst/oxyde
Project-URL: Issues, https://github.com/mr-fatalyst/oxyde/issues
Keywords: orm,async,database,postgresql,sqlite,mysql,pydantic
Classifier: Development Status :: 4 - Beta
Classifier: Intended Audience :: Developers
Classifier: License :: OSI Approved :: MIT License
Classifier: Programming Language :: Python :: 3
Classifier: Programming Language :: Python :: 3.10
Classifier: Programming Language :: Python :: 3.11
Classifier: Programming Language :: Python :: 3.12
Classifier: Programming Language :: Python :: 3.13
Classifier: Programming Language :: Python :: 3.14
Classifier: Programming Language :: Rust
Classifier: Framework :: AsyncIO
Classifier: Topic :: Database
Classifier: Typing :: Typed
Requires-Python: >=3.10
Requires-Dist: pydantic>=2.0
Requires-Dist: msgpack>=1.0
Requires-Dist: typer>=0.9
Requires-Dist: oxyde-core<0.4.0,>=0.3.0
Provides-Extra: dev
Requires-Dist: pytest>=9.0; extra == "dev"
Requires-Dist: pytest-asyncio>=1.0; extra == "dev"
Requires-Dist: pytest-cov>=7.0; extra == "dev"
Requires-Dist: ruff>=0.14.7; extra == "dev"
Requires-Dist: pre-commit>=4.5.0; extra == "dev"
